DecisionTreeBktUtil/__init__.py
DecisionTreeBktUtil/bkt_utils.py
DecisionTreeBktUtil/getColBktFromDF.py
DecisionTreeBktUtil/main.py
ZHUANZHUANBktUtil-2.1.1.dist-info/METADATA
ZHUANZHUANBktUtil-2.1.1.dist-info/WHEEL
ZHUANZHUANBktUtil-2.1.1.dist-info/top_level.txt
ZHUANZHUANBktUtil-2.1.1.dist-info/RECORD
